<?xml version="1.0" encoding="UTF-8"?>

<channel name="xfce4-panel" version="1.0">
  <property name="configver" type="empty"/>
  <property name="panels" type="empty">
    <property name="panel-1" type="empty">
      <property name="position" type="empty"/>
      <property name="length" type="empty"/>
      <property name="position-locked" type="empty"/>
      <property name="size" type="uint" value="32"/>
      <property name="length-adjust" type="empty"/>
      <property name="plugin-ids" type="array">
        <value type="int" value="1"/>
        <value type="int" value="2"/>
        <value type="int" value="3"/>
        <value type="int" value="4"/>
        <value type="int" value="5"/>
        <value type="int" value="8"/>
        <value type="int" value="6"/>
        <value type="int" value="13"/>
        <value type="int" value="7"/>
        <value type="int" value="9"/>
        <value type="int" value="10"/>
        <value type="int" value="11"/>
        <value type="int" value="14"/>
      </property>
      <property name="background-style" type="uint" value="1"/>
      <property name="background-rgba" type="array">
        <value type="double" value="0.447059"/>
        <value type="double" value="0.623529"/>
        <value type="double" value="0.811765"/>
        <value type="double" value="1.000000"/>
      </property>
      <property name="leave-opacity" type="uint" value="100"/>
    </property>
  </property>
  <property name="plugins" type="empty">
    <property name="plugin-1" type="empty"/>
    <property name="plugin-2" type="empty">
      <property name="style" type="empty"/>
    </property>
    <property name="plugin-3" type="empty"/>
    <property name="plugin-4" type="empty">
      <property name="flat-buttons" type="empty"/>
      <property name="show-handle" type="empty"/>
      <property name="grouping" type="uint" value="1"/>
      <property name="sort-order" type="uint" value="2"/>
      <property name="show-wireframes" type="bool" value="true"/>
      <property name="show-only-minimized" type="bool" value="false"/>
    </property>
    <property name="plugin-5" type="empty">
      <property name="expand" type="empty"/>
      <property name="style" type="empty"/>
    </property>
    <property name="plugin-6" type="empty">
      <property name="enable-keyboard-shortcuts" type="bool" value="true"/>
      <property name="mpris-players" type="string" value="chromium.instance1014;firefox.instance2848;firefox.instance32331"/>
    </property>
    <property name="plugin-14" type="empty"/>
    <property name="plugin-13" type="empty"/>
    <property name="plugin-7" type="empty">
      <property name="show-frame" type="empty"/>
      <property name="square-icons" type="empty"/>
      <property name="icon-size" type="int" value="0"/>
      <property name="symbolic-icons" type="empty"/>
      <property name="known-items" type="array">
        <value type="string" value="Signal1"/>
        <value type="string" value="nm-applet"/>
        <value type="string" value="org.guido-berhoerster.code.package-update-indicator"/>
      </property>
      <property name="known-legacy-items" type="array">
        <value type="string" value="zim"/>
        <value type="string" value="ibus panel"/>
        <value type="string" value="ibus-ui-gtk3"/>
      </property>
      <property name="hidden-items" type="array">
        <value type="string" value="org.guido-berhoerster.code.package-update-indicator"/>
      </property>
      <property name="single-row" type="bool" value="false"/>
    </property>
    <property name="plugin-15" type="empty">
      <property name="menu-is-primary" type="empty"/>
      <property name="square-icons" type="empty"/>
      <property name="icon-size" type="empty"/>
      <property name="symbolic-icons" type="empty"/>
    </property>
    <property name="plugin-8" type="empty">
      <property name="rows" type="uint" value="2"/>
      <property name="miniature-view" type="bool" value="true"/>
    </property>
    <property name="plugin-9" type="empty">
      <property name="style" type="empty"/>
    </property>
    <property name="plugin-10" type="empty">
      <property name="show-frame" type="empty"/>
      <property name="digital-format" type="string" value="%_H:%M"/>
      <property name="timezone" type="string" value="Europe/Berlin"/>
    </property>
    <property name="plugin-11" type="empty">
      <property name="style" type="empty"/>
    </property>
  </property>
</channel>
